setup.py
echowall/__init__.py
echowall/app/__init__.py
echowall/app/base.py
echowall/app/client.py
echowall/app/conf.py
echowall/app/consts.py
echowall/app/consumer.py
echowall/app/exceptions.py
echowall/app/message.py
echowall/app/producer.py
echowall/app/puch_consumer_callback.py
echowall/factory/__init__.py
echowall/factory/consumer.py
echowall/factory/message.py
echowall/factory/producer.py
echowall/rocket_mq/__init__.py
echowall/rocket_mq/consumer.py
echowall/rocket_mq/consumer_impl.py
echowall/rocket_mq/message.py
echowall/rocket_mq/producer.py
echowall/rocket_mq/producer_impl.py
echowall/utils/__init__.py
echowall/utils/regex_tools.py
echowall/utils/singleton.py
echowall-2.6.7.dist-info/LICENSE.rst
echowall-2.6.7.dist-info/METADATA
echowall-2.6.7.dist-info/WHEEL
echowall-2.6.7.dist-info/top_level.txt
echowall-2.6.7.dist-info/RECORD
