Metadata-Version: 2.1
Name: echowall
Version: 2.6.7
Summary: UNKNOWN
Author: ww166
Author-email: ww166mail@gmail.com
License: MIT
Project-URL: GitHub, https://github.com/ww166/echowall
Keywords: RocketMQ,MessageQueue
Platform: UNKNOWN
Classifier: Development Status :: 3 - Alpha
Classifier: Intended Audience :: Developers
Classifier: Topic :: Software Development :: Documentation
Classifier: License :: OSI Approved :: MIT License
Classifier: Programming Language :: Python :: 3
Classifier: Programming Language :: Python :: 3.6
Classifier: Programming Language :: Python :: 3.7
Classifier: Programming Language :: Python :: 3.8
Classifier: Programming Language :: Python :: 3.9
Classifier: Programming Language :: Python :: 3.10
License-File: LICENSE.rst
Requires-Dist: rocketmq-client-python (==2.0.0)
Requires-Dist: snowflake-id (==0.0.2)
